Workbook

Sheet Summary
A1: SyndicSage V5 — Cost & Systems Overview
A2: All amounts in EUR · Updated 2026-05-27
A4: One-Time Setup | B4: Monthly (MVP) | C4: Annual (MVP) | E4: Monthly at Scale | F4: Break-Even (€49/mo plan)
A6: ='One-Time Costs'!B2 | B6: ='Monthly Costs'!C2 | C6: ='Monthly Costs'!C3 | E6: ='Monthly Costs'!C4 | F6: ='Break-Even'!B4
A9: Phase Cost Milestones
A10: Phase | B10: Name | C10: New Services Added | D10: Extra Monthly Cost | E10: Cumulative Monthly
A11: Phase 0-1 | B11: Foundation + Shell | C11: Supabase Pro, Railway, Vercel, GitHub Private | D11: €61 | E11: €61
A12: Phase 2 | B12: Core Data | C12: Google Workspace (already set up) | D12: €0 | E12: €61
A13: Phase 3 | B13: Communication | C13: Resend (free tier), Sentry (free tier) | D13: €0 | E13: €61
A14: Phase 4 | B14: Intelligence | C14: Anthropic API (usage-based), Upstash Redis | D14: €30 | E14: €91
A15: Phase 5 | B15: Governance | C15: No new services | D15: €0 | E15: €91
A16: Phase 6 | B16: Portal | C16: Resend scaling (more emails) | D16: €20 | E16: €111
A17: Phase 7 | B17: Mobile | C17: Apple Developer ($99/yr), Expo EAS Build | D17: €18 | E17: €129
A18: Phase 8 | B18: Launch | C18: Vercel Pro (custom domain + bandwidth), DPA sign-offs | D18: €20 | E18: €149

Sheet Monthly Costs
A1: Monthly Recurring Costs
A2: Total Monthly (MVP — Phase 0-3) | B2: =SUMIF(E5:E100,"MVP",D5:D100)
A3: Total Monthly (Full — all phases) | B3: =SUM(D5:D100)
A4: Total Monthly at Scale (estimate) | B4: =SUMIF(E5:E100,"Scale",D5:D100)+SUMIF(E5:E100,"MVP",D5:D100)
A5: Service | B5: Category | C5: Plan / Tier | D5: EUR / Month | E5: Phase | F5: Status | G5: Notes
A6: Supabase | B6: Infrastructure | C6: Pro (EU region) | D6: 25 | E6: MVP | F6: Required | G6: PostgreSQL + Auth + Storage + Realtime. EU region mandatory for GDPR. Daily backups.
A7: Railway — API | B7: Infrastructure | C7: Starter + usage | D7: 8 | E7: MVP | F7: Required | G7: Hono API server. ~€8/mo for small workloads. Scales with usage.
A8: Railway — Worker | B8: Infrastructure | C8: Starter + usage | D8: 7 | E8: MVP | F8: Required | G8: BullMQ worker (email, scan, PDF, AI jobs). Separate service from API.
A9: Vercel | B9: Infrastructure | C9: Hobby (free → Pro at launch) | D9: 0 | E9: MVP | F9: Free now | G9: Hobby supports custom domains. Upgrade to Pro (€20/mo) at launch for bandwidth + team.
A10: GitHub | B10: Development | C10: Free → Team (private repo) | D10: 0 | E10: MVP | F10: Free now | G10: Switch to private before launch. Team plan: $4/user/mo. Solo: free with GitHub Pro ($4/mo).
A11: Google Workspace | B11: Communication | C11: Business Starter | D11: 6 | E11: MVP | F11: Active | G11: hello@syndicsage.com already set up. MX records propagated 2026-05-24.
A12: Upstash Redis | B12: Infrastructure | C12: Free tier → Pay-as-you-go | D12: 0 | E12: MVP | F12: Free now | G12: Rate limiting + BullMQ queue. Free: 10k commands/day. ~€5/mo at scale.
A13: Resend | B13: Communication | C13: Free (3,000 emails/mo) | D13: 0 | E13: MVP | F13: Free now | G13: Transactional email. Free tier sufficient until Portal launch. Scale plan: €20/mo for 50k.
A14: Sentry | B14: Monitoring | C14: Free (Developer) | D14: 0 | E14: MVP | F14: Free now | G14: Error tracking + performance. Free tier: 5k errors/mo. Team: $26/mo when needed.
A15: Anthropic API | B15: AI | C15: Usage-based (Claude Sonnet) | D15: 20 | E15: Phase 4 | F15: Required | G15: AI Sage chat + extraction + summarization. €20/mo estimate for low usage. Scales with users.
A16: Expo EAS Build | B16: Mobile | C16: Free → Production | D16: 0 | E16: Phase 7 | F16: Free now | G16: Mobile build service. Free: 30 builds/mo. Production plan: $99/mo if needed.
A17: Vercel Pro | B17: Infrastructure | C17: Pro | D17: 20 | E17: Phase 8 | F17: At launch | G17: Upgrade at launch for bandwidth, analytics, team access. €20/mo.
... A20: Plausible | B20: Analytics | C20: Starter | D20: 9 | E20: Optional | F20: Optional | G20: Privacy-friendly analytics alternative to Google Analytics. GDPR-compliant.
A21: TOTAL (all services) | D21: =SUM(D6:D20)

Sheet One-Time Costs
A1: One-Time & Annual Costs
A2: Total One-Time (Pre-Launch Minimum) | D2: =SUMIF(E5:E100,"One-time",C5:C100)
A3: Total Annual (recurring yearly) | D3: =SUMIF(E5:E100,"Annual",C5:C100)
A5: Item | B5: Category | C5: EUR | D5: Priority | E5: Frequency | F5: Phase | G5: Notes
A6: Namecheap — syndicsage.com | B6: Domain | C6: 12 | D6: Required | E6: Annual | F6: Live | G6: Already purchased. Renews ~€12/yr. Includes DNS management.
A7: Google Workspace | B7: Communication | C7: 72 | D7: Required | E7: Annual | F7: Active | G7: €6/mo = €72/yr. hello@syndicsage.com. MX records set.
A8: EUIPO Trademark — SyndicSage | B8: Legal | C8: 900 | D8: High | E8: One-time | F8: Pre-launch | G8: Class 42+35. DIY via euipo.europa.eu Easy Filing. 4-6 months processing.
A9: Privacy Policy + Terms of Use | B9: Legal | C9: 0 | D9: Required | E9: One-time | F9: Pre-launch | G9: Use iubenda.com (€27/yr) or lawyer (€500-2000). Must be live before first user.
A10: GDPR DPA — Supabase | B10: Legal/GDPR | C10: 0 | D10: Required | E10: One-time | F10: Pre-launch | G10: Free. Sign via Supabase dashboard under Settings > Legal.
A11: GDPR DPA — Vercel | B11: Legal/GDPR | C11: 0 | D11: Required | E11: One-time | F11: Pre-launch | G11: Free. Sign via Vercel dashboard under Settings > Legal.
A12: GDPR DPA — Resend | B12: Legal/GDPR | C12: 0 | D12: Required | E12: One-time | F12: Pre-launch | G12: Free. Sign via Resend dashboard.
A13: GDPR DPA — Anthropic | B13: Legal/GDPR | C13: 0 | D13: Required | E13: One-time | F13: Phase 4 | G13: Free. Anthropic provides standard DPA. Sign before AI features go live.
A14: GDPR DPA — Railway | B14: Legal/GDPR | C14: 0 | D14: Required | E14: One-time | F14: Pre-launch | G14: Free. Contact Railway support for DPA.
A15: Apple Developer Program | B15: Mobile | C15: 99 | D15: Required | E15: Annual | F15: Phase 7 | G15: Required to publish on App Store. $99/yr. Enables Apple Sign In on mobile.
A16: Google Play Console | B16: Mobile | C16: 25 | D16: Required | E16: One-time | F16: Phase 7 | G16: One-time $25 registration fee to publish on Google Play.
A17: iubenda Privacy Policy | B17: Legal | C17: 27 | D17: Recommended | E17: Annual | F17: Pre-launch | G17: GDPR-compliant privacy policy generator. Covers Belgium/EU. €27/yr.
... A20: External Pentest | B20: Security | C20: 2000 | D20: Deferred | E20: One-time | F20: Phase 8+ | G20: Trigger: first enterprise contract or €50k ARR. OWASP Top 10 + tenant isolation.
A21: TOTAL ONE-TIME (Required only) | C21: =SUMIF(D6:D20,"Required",C6:C20)+SUMIF(D6:D20,"High",C6:C20)

Sheet Accounts & Access
A1: All Accounts, Logins & Access — SyndicSage V5
A2: Service | B2: URL | C2: Account / Login | D2: Purpose | E2: Tier | F2: Status | G2: Monthly Cost
A3: Supabase | B3: supabase.com | C3: chrisndi-syn account | D3: PostgreSQL DB + Auth + Storage + Realtime | E3: Pro | F3: Active | G3: €25
A4: Vercel | B4: vercel.com | C4: chrisndi-syn account | D4: Frontend hosting — app.syndicsage.com | E4: Hobby → Pro | F4: Active | G4: €0 → €20
A5: Railway | B5: railway.app | C5: chrisndi-syn account | D5: Hono API + BullMQ Worker hosting | E5: Starter | F5: Active | G5: €15
A6: GitHub | B6: github.com/chrisndi-syn | C6: chrisndi-syn | D6: Source code — SyndicSage repo (go private!) | E6: Free → Team | F6: Public ⚠️ | G6: €0 → €4
A7: Google Workspace | B7: workspace.google.com | C7: hello@syndicsage.com | D7: Business email + Google Sign In OAuth | E7: Business Starter | F7: Active | G7: €6
A8: Anthropic | B8: console.anthropic.com | C8: chris account | D8: Claude API — AI Sage features | E8: Pay-as-you-go | F8: Ready | G8: €20+
A9: Namecheap | B9: namecheap.com | C9: chris account | D9: syndicsage.com domain + DNS | E9: Domain | F9: Active | G9: €1/mo
A10: Resend | B10: resend.com | C10: chrisndi-syn account | D10: Transactional email (invites, reminders) | E10: Free | F10: Set up | G10: €0
A11: Upstash | B11: upstash.com | C11: chrisndi-syn account | D11: Redis — rate limiting + BullMQ queue | E11: Free | F11: Set up | G11: €0
A12: Sentry | B12: sentry.io | C12: chrisndi-syn account | D12: Error tracking + performance monitoring | E12: Free | F12: Set up | G12: €0
A13: Apple Developer | B13: developer.apple.com | C13: chris Apple ID | D13: App Store publishing + Apple Sign In | E13: Standard ($99/yr) | F13: Phase 7 | G13: €8/mo
... A17: PostHog | B17: posthog.com | C17: chrisndi-syn account | D17: Product analytics (optional) | E17: Free | F17: Optional | G17: €0

Sheet Phase Rollout
A1: Cost Rollout by Phase
A2: Phase | B2: Name | C2: Services Activated | D2: New Monthly Cost | E2: Cumulative Monthly | F2: One-Time This Phase | G2: Cumulative One-Time | H2: Notes
A3: Phase 0 | B3: Architecture Foundation | C3: Supabase Pro, Railway API, Railway Worker, Upstash Redis (free) | D3: 40 | E3: 40 | F3: 0 | G3: 0 | H3: Core infrastructure spun up. No users yet.
A4: Phase 1 | B4: Shell | C4: GitHub Team (private repo), Google Workspace | D4: 21 | E4: 61 | F4: 0 | G4: 0 | H4: Login page live. Repo goes private.
A5: Phase 2 | B5: Core Data | C5: No new services | D5: 0 | E5: 61 | F5: 0 | G5: 0 | H5: Buildings, owners, charges, settings.
A6: Phase 2.5 | B6: Audit Foundation | C6: No new services | D6: 0 | E6: 61 | F6: 0 | G6: 0 | H6: Audit log + GDPR table created.
A7: Phase 3 | B7: Communication | C7: Resend (free), Sentry (free) | D7: 0 | E7: 61 | F7: 0 | G7: 0 | H7: Documents, inbox, timeline, tickets.
A8: Phase 4 | B8: Intelligence | C8: Anthropic API | D8: 20 | E8: 81 | F8: 0 | G8: 0 | H8: AI Sage, extraction, RAG. Cost scales with usage.
A9: Phase 5 | B9: Governance | C9: No new services | D9: 0 | E9: 81 | F9: 0 | G9: 0 | H9: Roadmap, voting, meetings, reporting.
A10: Phase 6 | B10: Portal | C10: Resend Scale (more emails) | D10: 20 | E10: 101 | F10: 0 | G10: 0 | H10: Resident portal live. Email volume increases.
A11: Phase 7 | B11: Mobile | C11: Apple Developer ($99/yr), Google Play (€25 once) | D11: 8 | E11: 109 | F11: 124 | G11: 124 | H11: iOS + Android. Apple Dev €99/yr = €8/mo equiv.
A12: Phase 8 | B12: Launch | C12: Vercel Pro, iubenda, trademark filed | D12: 29 | E12: 138 | F12: 927 | G12: 1051 | H12: Vercel Pro €20 + iubenda €2 + GitHub Team already counted.

Sheet Break-Even
A1: Break-Even & Revenue Projection
A2: Pricing Assumptions
A3: Parameter | B3: Value | C3: Unit
A4: Starter plan price | B4: 49 | C4: €/month per customer
A5: Pro plan price | B5: 99 | C5: €/month per customer
A6: Enterprise plan price | B6: 199 | C6: €/month per customer
A7: Monthly costs (MVP) | B7: 61 | C7: €/month (Phase 0-3 baseline)
A8: Monthly costs (Launch) | B8: 138 | C8: €/month (Phase 8 full)
A10: Break-Even Analysis
A11: Break-even (MVP costs, Starter plan) | B11: =CEILING(B8/B4,1)
A12: Break-even (Launch costs, Starter plan) | B12: =CEILING(B9/B4,1)
A14: Revenue Projection
A15: Customers | B15: Starter (€49) | C15: Pro (€99) | D15: Mixed (50/50) | E15: Profit (Mixed - Launch costs)
A16: 1 | B16: =A16*B4 | C16: =A16*B5 | D16: =A16*(B4+B5)/2 | E16: =D16-B9
A17: 2 | B17: =A17*B4 | C17: =A17*B5 | D17: =A17*(B4+B5)/2 | E17: =D17-B9
A18: 3 | B18: =A18*B4 | C18: =A18*B5 | D18: =A18*(B4+B5)/2 | E18: =D18-B9
A19: 5 | B19: =A19*B4 | C19: =A19*B5 | D19: =A19*(B4+B5)/2 | E19: =D19-B9
A20: 10 | B20: =A20*B4 | C20: =A20*B5 | D20: =A20*(B4+B5)/2 | E20: =D20-B9
A21: 20 | B21: =A21*B4 | C21: =A21*B5 | D21: =A21*(B4+B5)/2 | E21: =D21-B9
A22: 50 | B22: =A22*B4 | C22: =A22*B5 | D22: =A22*(B4+B5)/2 | E22: =D22-B9
A23: 100 | B23: =A23*B4 | C23: =A23*B5 | D23: =A23*(B4+B5)/2 | E23: =D23-B9
A25: Note: Break-even is at 3 customers on Starter plan (MVP phase). At launch costs, 3 customers still covers it. First €49 customer = profitable at MVP stage.

Sheet Deferred Costs
A1: Deferred & Future Costs (not in MVP budget)
A2: Item | B2: Estimated Cost | C2: Frequency | D2: Trigger | E2: Notes
A3: Self-hosted Supabase (EU VPS) | B3: €20-50/mo | C3: Monthly | D3: Enterprise client requires on-premise | E3: Supabase is open source — self-host entire stack on Hetzner/OVH EU VPS.
A4: MinIO (document storage) | B4: €10-30/mo | C4: Monthly | D4: On-premise contract or DPA requirement | E4: S3-compatible. Same path structure. Zero code changes.
A5: itsme® authentication | B5: €0.10-0.30/tx | C5: Per login | D5: Enterprise/government customer request | E5: OIDC — plugs into Supabase as custom OAuth. Contact itsme.be/business.
A6: External pentest | B6: €1,500-3,000 | C6: One-time | D6: First enterprise contract or €50k ARR | E6: OWASP Top 10 + tenant isolation + file upload attack vectors.
A7: LaunchDarkly (feature flags) | B7: €0-350/mo | C7: Monthly | D7: Team grows beyond 3 devs | E7: Current plan: feature_flags Supabase table (free). LaunchDarkly when ops complexity grows.
A8: Read replica (Supabase) | B8: ~€25/mo extra | C8: Monthly | D8: DB query latency > 200ms on list endpoints | E8: Supabase one-click. Route reads to replica, writes to primary.
A9: Kubernetes / EKS | B9: €200+/mo | C9: Monthly | D9: Railway costs > €500/mo or GPU workloads needed | E9: Hono is container-native — zero code changes to migrate.
A10: SOC 2 / ISO 27001 audit | B10: €5,000-20,000 | C10: One-time | D10: Enterprise procurement checklist | E10: Architecture already designed to pass. AWS accounts needed for SOC 2.
A11: Field-level encryption (KMS) | B11: €50-100/mo | C11: Monthly | D11: Enterprise DPA requirement for IBAN/national IDs | E11: packages/crypto + KMS-backed envelope encryption. Additive change.
A12: Apple Developer (mobile) | B12: €99/yr | C12: Annual | D12: Phase 7 — mobile app | E12: Required for App Store. Already in One-Time budget.
A13: Expo EAS Production build | B13: $99/mo | C13: Monthly | D13: Mobile app CI/CD at scale | E13: Free tier: 30 builds/mo. Upgrade when release cadence increases.
A14: Multi-region (Vercel + Railway) | B14: €50-100/mo | C14: Monthly | D14: Customers outside Belgium require low latency | E14: Vercel edge already global. Railway: add EU + US regions.
